kipp/__init__.py
kipp/exceptions.py
kipp/aio/__init__.py
kipp/aio/base.py
kipp/aio/exceptions.py
kipp/aio/http.py
kipp/aio/sqlhelper.py
kipp/decorator/__init__.py
kipp/images/__init__.py
kipp/libs/__init__.py
kipp/libs/aio.py
kipp/libs/exceptions.py
kipp/models/__init__.py
kipp/models/base.py
kipp/models/exceptions.py
kipp/models/movoto.py
kipp/options/__init__.py
kipp/options/arguments.py
kipp/options/exceptions.py
kipp/options/mlogger.py
kipp/redis/__init__.py
kipp/redis/consts.py
kipp/redis/utils.py
kipp/runner/__init__.py
kipp/runner/__main__.py
kipp/runner/exceptions.py
kipp/runner/models.py
kipp/runner/runner.py
kipp/utils/__init__.py
kipp/utils/concurrents.py
kipp/utils/date.py
kipp/utils/dfa_filters.py
kipp/utils/logger.py
kipp/utils/mailsender.py
kipp-0.3.2.data/data/CHANGELOG.md
kipp-0.3.2.data/data/LICENSE
kipp-0.3.2.data/data/Makefile
kipp-0.3.2.data/data/README.md
kipp-0.3.2.data/data/package.json
kipp-0.3.2.data/data/requirements.txt
kipp-0.3.2.data/data/tox.ini
kipp-0.3.2.dist-info/LICENSE
kipp-0.3.2.dist-info/METADATA
kipp-0.3.2.dist-info/WHEEL
kipp-0.3.2.dist-info/entry_points.txt
kipp-0.3.2.dist-info/top_level.txt
kipp-0.3.2.dist-info/RECORD
