Metadata-Version: 2.2
Name: kipp
Version: 0.3.2
Summary: Python Utils
Home-page: https://github.com/Laisky/kipp
Author: Laisky
Author-email: ppcelery@gmail.com
License: MIT License
Keywords: setup,distutils,utils
Classifier: Development Status :: 4 - Beta
Classifier: Development Status :: 4 - Beta
Classifier: Topic :: Software Development :: Libraries
Classifier: Environment :: Web Environment
Classifier: Intended Audience :: Developers
Classifier: License :: OSI Approved :: MIT License
Classifier: Operating System :: OS Independent
Classifier: Programming Language :: Python
Classifier: Programming Language :: Python :: 2.7
Classifier: Programming Language :: Python :: 3.6
Classifier: Programming Language :: Python :: 3.7
Classifier: Programming Language :: Python :: 3.8
License-File: LICENSE
Requires-Dist: ruamel.yaml~=0.14
Requires-Dist: future<1
Requires-Dist: maya~=0.6
Requires-Dist: tornado>=6.3.3
Requires-Dist: xxhash~=1.3
Requires-Dist: redis~=5.2.1
Provides-Extra: test
Requires-Dist: pytest; extra == "test"
Requires-Dist: mock; extra == "test"
Provides-Extra: doc
Requires-Dist: sphinx; extra == "doc"
Requires-Dist: recommonmark; extra == "doc"
Requires-Dist: sphinxcontrib-napoleon; extra == "doc"
Provides-Extra: image
Requires-Dist: pillow==3.4.2; extra == "image"
Provides-Extra: aio
Requires-Dist: tornado~=4.5; extra == "aio"
Provides-Extra: all
Requires-Dist: pytest; extra == "all"
Requires-Dist: mock; extra == "all"
Requires-Dist: sphinx; extra == "all"
Requires-Dist: recommonmark; extra == "all"
Requires-Dist: sphinxcontrib-napoleon; extra == "all"
Requires-Dist: pillow==3.4.2; extra == "all"
Requires-Dist: tornado~=4.5; extra == "all"
Dynamic: author
Dynamic: author-email
Dynamic: classifier
Dynamic: description
Dynamic: home-page
Dynamic: keywords
Dynamic: license
Dynamic: provides-extra
Dynamic: requires-dist
Dynamic: summary
